CHANGELOG.md
README.md
mitol/__init__.py
mitol/uvtestapp/__init__.py
mitol/uvtestapp/api.py
mitol/uvtestapp/apps.py
mitol/uvtestapp/py.typed
mitol/uvtestapp/settings/__init__.py
mitol_django_uvtestapp-2024.10.24.dist-info/METADATA
mitol_django_uvtestapp-2024.10.24.dist-info/WHEEL
mitol_django_uvtestapp-2024.10.24.dist-info/RECORD
