Metadata-Version: 2.3
Name: mitol-django-uvtestapp
Version: 2024.10.24
Summary: MIT Open Learning Django app template
License-Expression: BSD-3-Clause
Requires-Python: >=3.8
Requires-Dist: django-stubs>=1.13.1
Requires-Dist: django>=3.0
Requires-Dist: edx-opaque-keys==2.2.2
